honeycomb_io/__init__.py
honeycomb_io/cameras.py
honeycomb_io/coordinate_spaces.py
honeycomb_io/core.py
honeycomb_io/datapoints.py
honeycomb_io/devices.py
honeycomb_io/environments.py
honeycomb_io/exceptions.py
honeycomb_io/inference_executions.py
honeycomb_io/interactions.py
honeycomb_io/materials.py
honeycomb_io/persons.py
honeycomb_io/poses.py
honeycomb_io/schema.py
honeycomb_io/trays.py
honeycomb_io/utils.py
honeycomb_io/uwb_data.py
wf_honeycomb_io-2.1.2.dist-info/LICENSE
wf_honeycomb_io-2.1.2.dist-info/METADATA
wf_honeycomb_io-2.1.2.dist-info/WHEEL
wf_honeycomb_io-2.1.2.dist-info/top_level.txt
wf_honeycomb_io-2.1.2.dist-info/RECORD
