Metadata-Version: 2.1
Name: wf-honeycomb-io
Version: 2.1.2
Summary: Tools for working with data in Wildflower's Honeycomb database
Home-page: https://github.com/WildflowerSchools/wf-honeycomb-io
Author: Theodore Quinn
Author-email: ted.quinn@wildflowerschools.org
License: UNKNOWN
Keywords: database
Platform: UNKNOWN
Classifier: Intended Audience :: Developers
Classifier: License :: OSI Approved :: MIT License
Classifier: Operating System :: OS Independent
Classifier: Programming Language :: Python
License-File: LICENSE
Requires-Dist: wf-minimal-honeycomb-python (>=0.6.0)
Requires-Dist: pandas (>=1.2.2)
Requires-Dist: numpy (>=1.20.1)
Requires-Dist: boto3 (>=1.17)
Requires-Dist: inflection (>=0.5.1)
